{
    "name" : "bathroom-layout-1",
    "minimumWidth" : 6,
    "minimumHeight" : 6,
    "zones" : [
        {
            "width" : "w",
            "height" : "2",
            "x" : 0,
            "y" : "h-2",
            "tags" : [
                "toilet"
            ],
            "dirX" : 0,
            "dirY" : 1,
            "fillType" : "simple"

        },{
            "width" : "4",
            "height" : "2",
            "x" : 1,
            "y" : 0,
            "tags" : [
                "sink"
            ],
            "dirX" : 0,
            "dirY" : -1,
            "fillType" : "simple"

        },{
            "width" : "2",
            "height" : "1",
            "x" : 0,
            "y" : 0,
            "tags" : [
                "sink"
            ],
            "dirX" : 0,
            "dirY" : -1,
            "fillType" : "towel-dispenser"

        }
         
    ]

}